NUTS_calkit/Manuscript of NUTS_calkit.txt
NUTS_calkit/NUTS_calkit.py
NUTS_calkit/__init__.py
NUTS_calkit/main_program.py
nuts_calkit-0.0.6.dist-info/METADATA
nuts_calkit-0.0.6.dist-info/WHEEL
nuts_calkit-0.0.6.dist-info/licenses/LICENSE.txt
nuts_calkit-0.0.6.dist-info/RECORD
