Metadata-Version: 2.4
Name: NUTS_calkit
Version: 0.0.6
Summary: Non-Uniform Temperature Steel beam Calculation toolKit 
Project-URL: Homepage, https://github.com/Supernova772/NUTS_calkit
Author-email: Yang Li <yang.li-5@manchester.ac.uk>
License-File: LICENSE.txt
Classifier: License :: OSI Approved :: MIT License
Classifier: Operating System :: OS Independent
Classifier: Programming Language :: Python :: 3
Requires-Python: >=3.8
